{
  "규범 양태": {
    "RU": [
      {
        "label": "может",
        "regex": "\\bможет\\b"
      },
      {
        "label": "вправе",
        "regex": "\\bвправе\\b"
      },
      {
        "label": "признаётся/признается",
        "regex": "\\bпризна[её]тся\\b"
      },
      {
        "label": "подлежит/подлежат",
        "regex": "\\bподлеж(ит|ат)\\b"
      },
      {
        "label": "обязан(+성/수 변화)",
        "regex": "\\bобязан(а|о|ы)?\\b"
      },
      {
        "label": "должен(+성/수 변화)",
        "regex": "\\bдолжен(а|о|ы)?\\b"
      },
      {
        "label": "запрещается/запрещено",
        "regex": "\\bзапреща(ется|ются)\\b|\\bзапрещен[оы]\\b"
      },
      {
        "label": "допускается/допускаются",
        "regex": "\\bдопуска(ется|ются)\\b"
      },
      {
        "label": "считается",
        "regex": "\\bсчитаетс[яь]\\b"
      }
    ],
    "KO": [
      {
        "label": "정한다/규정한다",
        "regex": "정한다\\b|규정한다\\b"
      },
      {
        "label": "하여야 한다/해야 한다",
        "regex": "(하|하여)야\\s*한다\\b|해야\\s*한다\\b"
      },
      {
        "label": "할 수 있다/수 있다",
        "regex": "할\\s*수\\s*있다\\b|\\b수\\s*있다\\b"
      },
      {
        "label": "…아니한다/…않는다(금지)",
        "regex": "(아니|않)한다\\b|금지한다\\b"
      },
      {
        "label": "간주한다/본다",
        "regex": "(간주|본)다\\b"
      },
      {
        "label": "하도록 한다",
        "regex": "하도록\\s*한다\\b"
      }
    ]
  },
  "담화 결속 표지": {
    "RU": [
      {
        "label": "при этом",
        "regex": "\\bпри\\s+этом\\b"
      },
      {
        "label": "в частности",
        "regex": "\\bв\\s+частности\\b"
      },
      {
        "label": "таким образом",
        "regex": "\\bтаким\\s+образом\\b"
      },
      {
        "label": "кроме того",
        "regex": "\\bкроме\\s+того\\b"
      },
      {
        "label": "одновременно",
        "regex": "\\bодновременно\\b"
      },
      {
        "label": "вместе с тем",
        "regex": "\\bвместе\\s+с\\s+тем\\b"
      },
      {
        "label": "в том числе",
        "regex": "\\bв\\s+том\\s+числе\\b"
      }
    ],
    "KO": [
      {
        "label": "이에 따라",
        "regex": "\\b이에\\s*따라\\b"
      },
      {
        "label": "따라서",
        "regex": "\\b따라서\\b"
      },
      {
        "label": "특히",
        "regex": "\\b특히\\b"
      },
      {
        "label": "또한/아울러",
        "regex": "\\b(또한|아울러)\\b"
      },
      {
        "label": "이 경우",
        "regex": "\\b이\\s*경우(에는|에|엔)?\\b"
      },
      {
        "label": "이때",
        "regex": "\\b이\\s*때(는|에)?\\b"
      },
      {
        "label": "동시에/이와 함께",
        "regex": "\\b동시에\\b|\\b이와\\s*함께\\b"
      },
      {
        "label": "즉",
        "regex": "\\b즉\\b"
      },
      {
        "label": "한편",
        "regex": "\\b한편\\b"
      }
    ]
  },
  "대조/양보": {
    "RU": [
      {
        "label": "но",
        "regex": "\\bно\\b"
      },
      {
        "label": "однако",
        "regex": "\\bоднако\\b"
      },
      {
        "label": "тем не менее",
        "regex": "\\bтем\\s+не\\s+менее\\b"
      },
      {
        "label": "вместе с тем",
        "regex": "\\bвместе\\s+с\\s+тем\\b"
      }
    ],
    "KO": [
      {
        "label": "그러나",
        "regex": "\\b그러나\\b"
      },
      {
        "label": "다만",
        "regex": "\\b다만\\b"
      },
      {
        "label": "반면(에)",
        "regex": "\\b반면(에)?\\b"
      },
      {
        "label": "그럼에도 불구하고",
        "regex": "\\b그럼에도\\s*불구하고\\b"
      },
      {
        "label": "…아니한다/…않는다(금지와 충돌 가능)",
        "regex": "(아니|않)한다\\b"
      }
    ]
  },
  "법률 상용구": {
    "RU": [
      {
        "label": "в соответствии с",
        "regex": "\\bв\\s+соответствии\\s+с\\b"
      },
      {
        "label": "на основании",
        "regex": "\\bна\\s+основани[ийе]\\b"
      },
      {
        "label": "в отношении",
        "regex": "\\bв\\s+отношении\\b"
      },
      {
        "label": "в порядке",
        "regex": "\\bв\\s+порядке\\b"
      },
      {
        "label": "в целях",
        "regex": "\\bв\\s+целях\\b"
      },
      {
        "label": "в случае/в случаях",
        "regex": "\\bв\\s+случа(е|ях)\\b"
      },
      {
        "label": "согласно",
        "regex": "\\bсогласно\\b"
      },
      {
        "label": "в силу",
        "regex": "\\bв\\s+силу\\b"
      },
      {
        "label": "исходя из",
        "regex": "\\bисходя\\s+из\\b"
      }
    ],
    "KO": [
      {
        "label": "에 따라",
        "regex": "에\\s*따라\\b"
      },
      {
        "label": "에 의하여/의거하여",
        "regex": "에\\s*(의하여|의거(하여)?)\\b"
      },
      {
        "label": "에 관하여",
        "regex": "에\\s*관하여\\b"
      },
      {
        "label": "에 대한",
        "regex": "에\\s*대한\\b"
      },
      {
        "label": "의 경우",
        "regex": "\\b의\\s*경우(에는|에|엔)?\\b"
      },
      {
        "label": "을/를 대상으로",
        "regex": "(을|를)\\s*대상으로\\b"
      },
      {
        "label": "에 한하여",
        "regex": "에\\s*한하여\\b"
      }
    ]
  },
  "전치사": {
    "RU": [
      {
        "label": "в",
        "regex": "\\bв\\b"
      },
      {
        "label": "на",
        "regex": "\\bна\\b"
      },
      {
        "label": "по",
        "regex": "\\bпо\\b"
      },
      {
        "label": "при",
        "regex": "\\bпри\\b"
      },
      {
        "label": "для",
        "regex": "\\bдля\\b"
      },
      {
        "label": "о/об",
        "regex": "\\bо\\b|\\bоб\\b"
      },
      {
        "label": "от",
        "regex": "\\bот\\b"
      },
      {
        "label": "за",
        "regex": "\\bза\\b"
      },
      {
        "label": "с",
        "regex": "\\bс\\b"
      },
      {
        "label": "к",
        "regex": "\\bк\\b"
      },
      {
        "label": "из",
        "regex": "\\bиз\\b"
      },
      {
        "label": "у",
        "regex": "\\bу\\b"
      },
      {
        "label": "между",
        "regex": "\\bмежду\\b"
      }
    ],
    "KO": []
  },
  "접속사": {
    "RU": [
      {
        "label": "и",
        "regex": "\\bи\\b"
      },
      {
        "label": "или",
        "regex": "\\bили\\b"
      },
      {
        "label": "либо",
        "regex": "\\bлибо\\b"
      },
      {
        "label": "а также",
        "regex": "\\bа\\s+также\\b"
      }
    ],
    "KO": [
      {
        "label": "및",
        "regex": "\\b및\\b"
      },
      {
        "label": "또는",
        "regex": "\\b또는\\b"
      },
      {
        "label": "혹은",
        "regex": "\\b혹은\\b"
      }
    ]
  },
  "참조·근거 표지": {
    "RU": [
      {
        "label": "статья/статьи (형태 변화 포함)",
        "regex": "\\bстать(я|и|е|ю|ёй|ей|ями|ях)\\b"
      },
      {
        "label": "пункт/подпункт (형태 변화)",
        "regex": "\\bпод?пункт(а|е|у|ом|ы|ов|ами|ах)?\\b"
      },
      {
        "label": "часть (형태 변화)",
        "regex": "\\bчаст(ь|и|ях|ями)\\b"
      }
    ],
    "KO": [
      {
        "label": "제 N조",
        "regex": "제\\s?\\d+\\s*조\\b"
      },
      {
        "label": "제 N항",
        "regex": "제\\s?\\d+\\s*항\\b"
      },
      {
        "label": "제 N호/목",
        "regex": "제\\s?\\d+\\s*(호|목)\\b"
      },
      {
        "label": "조/항(단독표기 옵션)",
        "regex": "(?<!제\\s?\\d+\\s*)\\b(조|항)\\b"
      }
    ]
  },
  "참조·지시 표지": {
    "RU": [
      {
        "label": "настоящий (격 변화 포함)",
        "regex": "\\bнастоящ(ий|ая|ее|его|ему|ем|им|ие|их|ими|ую|ей)\\b"
      },
      {
        "label": "указанный (격 변화 포함)",
        "regex": "\\bуказан(ный|ная|ное|ного|ному|ным|ные|ных|ными|ную|ной)\\b"
      },
      {
        "label": "вышеуказанный/нижеуказанный",
        "regex": "\\b(выше|ниже)указан(н\\w+)\\b"
      }
    ],
    "KO": [
      {
        "label": "해당/본/상기",
        "regex": "\\b(해당|본|상기)\\b"
      },
      {
        "label": "이 법/이 규정/이 조",
        "regex": "\\b이\\s*(법|규정|조)\\b"
      },
      {
        "label": "같은 조/같은 항/동 조/동 항",
        "regex": "\\b(같은|동)\\s*(조|항)\\b"
      }
    ]
  },
  "종속 논리 연결": {
    "RU": [
      {
        "label": "если",
        "regex": "\\bесли\\b"
      },
      {
        "label": "поскольку",
        "regex": "\\bпоскольку\\b"
      },
      {
        "label": "чтобы",
        "regex": "\\bчтобы\\b"
      },
      {
        "label": "ввиду того что",
        "regex": "\\bввиду\\s+того\\s+что\\b"
      },
      {
        "label": "в случае, если",
        "regex": "\\bв\\s+случае,\\s*если\\b"
      }
    ],
    "KO": [
      {
        "label": "만약",
        "regex": "\\b만약\\b"
      },
      {
        "label": "…하는/한/할 경우(에는/에)",
        "regex": "(하|한|할)\\s*경우(에는|에|엔)?\\b"
      },
      {
        "label": "의 경우(에는/에)",
        "regex": "\\b의\\s*경우(에는|에|엔)?\\b"
      },
      {
        "label": "…하기 위해(서)",
        "regex": "하기\\s*위해(서)?\\b"
      },
      {
        "label": "…때(에는/에)",
        "regex": "\\b때(에는|에)\\b"
      },
      {
        "label": "…로 인해/인하여",
        "regex": "로\\s*인(해|하여)\\b"
      }
    ]
  }
}
